rtl/Dec_No.vhd
library ieee;
use ieee.std_logic_1164.all;
use ieee.numeric_std.all;

entity Dec_No is
port(
	Cnt : in  std_logic_vector(2 downto 0);
	No  : out std_logic_vector(3 downto 0));

end entity;


architecture rtl of Dec_No is

begin
	process(Cnt) is
	begin
		
		case Cnt is
			when "000" =>
				No <= "0010";
			when "001" =>
				No <= "0000";
			when "010" =>
				No <= "0010";
			when "011" =>
				No <= "0100";
			when "100" =>
				No <= "0111";
			when "101" =>
				No <= "0000";
			when "110" =>
				No <= "0010";
			when "111" =>
				No <= "0000";
			when others =>
				No <= (others=>'0');
		end case;
	
	end process;

end architecture;

tb/tb_Odev1.vhd
library ieee;
use ieee.std_logic_1164.all;
use ieee.numeric_std.all;

entity tb_Odev1 is
end entity;

architecture sim of tb_Odev1 is

	signal Cnt : unsigned(2 downto 0) := "000";
	signal No : unsigned(3 downto 0);
	
begin  
	Dec1 : entity work.Dec_No(rtl)
	port map(
		Cnt => Cnt,
		No => No);
	
	process is
	begin
		wait for 10ns;
		Cnt <= Cnt + 1;
	end process;
		
end architecture;

dec_no.vcd
$date
	Wed Sep 03 04:35:25 2025
$end
$version
	ModelSim Version 10.5b
$end
$timescale
	1ps
$end

$scope module tb_odev1 $end
$var wire 1 ! Cnt [2] $end
$var wire 1 " Cnt [1] $end
$var wire 1 # Cnt [0] $end
$var wire 1 $ No [3] $end
$var wire 1 % No [2] $end
$var wire 1 & No [1] $end
$var wire 1 ' No [0] $end

$scope module Dec1 $end
$var wire 1 ! Cnt [2] $end
$var wire 1 " Cnt [1] $end
$var wire 1 # Cnt [0] $end
$var wire 1 $ No [3] $end
$var wire 1 % No [2] $end
$var wire 1 & No [1] $end
$var wire 1 ' No [0] $end
$upscope $end
$upscope $end
$enddefinitions $end
#0
$dumpvars
0!
0"
0#
0$
0%
1&
0'
$end
#10000
1#
0&
#20000
0#
1"
1&
#30000
1#
0&
1%
#40000
0#
0"
1!
1'
1&
#50000
1#
0'
0&
0%
#60000
0#
1"
1&
#70000
1#
0&
#80000
0#
0"
0!
1&
$dumpoff
x!
x"
x#
x$
x%
x&
x'
$end
